<?xml version="1.0" encoding="utf-8" ?>
<dwsync>
<file name="jquery.js" server="C:/xampp/" local="130377789340000000" remote="130377789340000000" Dst="0" />
<file name="register.js" server="C:/xampp/" local="130395511516937854" remote="130395511510000000" Dst="0" />
<file name="login.js" server="C:/xampp/" local="130393736416752985" remote="130393736410000000" Dst="0" />
<file name="jquery.nyroModal.custom.js" server="C:/xampp/" local="130393657500000000" remote="130393657500000000" Dst="0" />
<file name="booking.js" server="C:/xampp/" local="130403194008448295" remote="130403194000000000" Dst="0" />
<file name="sessions.js" server="C:/xampp/" local="130403144532528435" remote="130403144530000000" Dst="0" />
<file name="rooms.js" server="C:/xampp/" local="130408370501807424" remote="130408370500000000" Dst="0" />
<file name="book.js" server="C:/xampp/" local="130408386092919798" remote="130408386090000000" Dst="0" />
</dwsync>